MainFunctionKernel.py
TestPackageforYouness-0.0.1.dist-info/LICENSE
TestPackageforYouness-0.0.1.dist-info/METADATA
TestPackageforYouness-0.0.1.dist-info/WHEEL
TestPackageforYouness-0.0.1.dist-info/top_level.txt
TestPackageforYouness-0.0.1.dist-info/RECORD
