Metadata-Version: 2.1
Name: TestPackageforYouness
Version: 0.0.1
Summary: Packaging Pipeline
Home-page: UNKNOWN
Author: Othmane ZARHALI
Author-email: ozarhali25@gmail.com
License: UNKNOWN
Platform: UNKNOWN
